ALU/XOR/XOR.v
module xor64bits(A,B,Ans);
    input [63:0]A;
    input [63:0]B;
    output [63:0]Ans;

    genvar i;
    for(i= 0;i<64; i=i+1)begin
        xor(Ans[i] , A[i], B[i]);
        // $display(Ans[i]);
        
    end

    //$monitor($time,"A=%b \n B=%b \n Out=%b\n", A,B, Ans);
      
endmodule

ALU/XOR/XOR_tb.v
`timescale 1ns/10ps
`include "XOR.v"
module XOR_tb;
    reg signed [63:0] A=64'b1111111111111111111111111111111111111111111111111111111111111111;
    reg signed [63:0] B=64'b1111111111111111111111111111111111111111111111111111111111111111;

    wire [63:0]Out;

    xor64bits ALU_XOR(A , B,  Out);

integer m = 1;
integer k, j;

initial begin
    $dumpfile("XOR_tb.vcd");
    $dumpvars(0,XOR_tb);
    
    
    $monitor($time,"\nA=%b\nB=%b\nOut=%b\n", A,B,Out);

    for(k = 0; k < 10; k = k + 1)
    begin
        A = A-1;
        for(j = 0; j < 10; j = j + 1)
        begin
            B = B-1;
            #5;
        end
        B=64'b1111111111111111111111111111111111111111111111111111111111111111;
    end

end

endmodule

ALU/XOR/XOR_tb.vcd
$date
	Tue Jan 24 15:05:12 2023
$end
$version
	Icarus Verilog
$end
$timescale
	10ps
$end
$scope module XOR_tb $end
$var wire 64 ! Out [63:0] $end
$var reg 64 " A [63:0] $end
$var reg 64 # B [63:0] $end
$var integer 32 $ j [31:0] $end
$var integer 32 % k [31:0] $end
$var integer 32 & m [31:0] $end
$scope module ALU_XOR $end
$var wire 64 ' A [63:0] $end
$var wire 64 ( B [63:0] $end
$var wire 64 ) Ans [63:0] $end
$scope begin genblk1[0] $end
$upscope $end
$scope begin genblk1[1] $end
$upscope $end
$scope begin genblk1[2] $end
$upscope $end
$scope begin genblk1[3] $end
$upscope $end
$scope begin genblk1[4] $end
$upscope $end
$scope begin genblk1[5] $end
$upscope $end
$scope begin genblk1[6] $end
$upscope $end
$scope begin genblk1[7] $end
$upscope $end
$scope begin genblk1[8] $end
$upscope $end
$scope begin genblk1[9] $end
$upscope $end
$scope begin genblk1[10] $end
$upscope $end
$scope begin genblk1[11] $end
$upscope $end
$scope begin genblk1[12] $end
$upscope $end
$scope begin genblk1[13] $end
$upscope $end
$scope begin genblk1[14] $end
$upscope $end
$scope begin genblk1[15] $end
$upscope $end
$scope begin genblk1[16] $end
$upscope $end
$scope begin genblk1[17] $end
$upscope $end
$scope begin genblk1[18] $end
$upscope $end
$scope begin genblk1[19] $end
$upscope $end
$scope begin genblk1[20] $end
$upscope $end
$scope begin genblk1[21] $end
$upscope $end
$scope begin genblk1[22] $end
$upscope $end
$scope begin genblk1[23] $end
$upscope $end
$scope begin genblk1[24] $end
$upscope $end
$scope begin genblk1[25] $end
$upscope $end
$scope begin genblk1[26] $end
$upscope $end
$scope begin genblk1[27] $end
$upscope $end
$scope begin genblk1[28] $end
$upscope $end
$scope begin genblk1[29] $end
$upscope $end
$scope begin genblk1[30] $end
$upscope $end
$scope begin genblk1[31] $end
$upscope $end
$scope begin genblk1[32] $end
$upscope $end
$scope begin genblk1[33] $end
$upscope $end
$scope begin genblk1[34] $end
$upscope $end
$scope begin genblk1[35] $end
$upscope $end
$scope begin genblk1[36] $end
$upscope $end
$scope begin genblk1[37] $end
$upscope $end
$scope begin genblk1[38] $end
$upscope $end
$scope begin genblk1[39] $end
$upscope $end
$scope begin genblk1[40] $end
$upscope $end
$scope begin genblk1[41] $end
$upscope $end
$scope begin genblk1[42] $end
$upscope $end
$scope begin genblk1[43] $end
$upscope $end
$scope begin genblk1[44] $end
$upscope $end
$scope begin genblk1[45] $end
$upscope $end
$scope begin genblk1[46] $end
$upscope $end
$scope begin genblk1[47] $end
$upscope $end
$scope begin genblk1[48] $end
$upscope $end
$scope begin genblk1[49] $end
$upscope $end
$scope begin genblk1[50] $end
$upscope $end
$scope begin genblk1[51] $end
$upscope $end
$scope begin genblk1[52] $end
$upscope $end
$scope begin genblk1[53] $end
$upscope $end
$scope begin genblk1[54] $end
$upscope $end
$scope begin genblk1[55] $end
$upscope $end
$scope begin genblk1[56] $end
$upscope $end
$scope begin genblk1[57] $end
$upscope $end
$scope begin genblk1[58] $end
$upscope $end
$scope begin genblk1[59] $end
$upscope $end
$scope begin genblk1[60] $end
$upscope $end
$scope begin genblk1[61] $end
$upscope $end
$scope begin genblk1[62] $end
$upscope $end
$scope begin genblk1[63] $end
$upscope $end
$upscope $end
$upscope $end
$enddefinitions $end
#0
$dumpvars
b0 )
b1111111111111111111111111111111111111111111111111111111111111110 (
b1111111111111111111111111111111111111111111111111111111111111110 '
b1 &
b0 %
b0 $
b1111111111111111111111111111111111111111111111111111111111111110 #
b1111111111111111111111111111111111111111111111111111111111111110 "
b0 !
$end
#500
b11 !
b11 )
b1111111111111111111111111111111111111111111111111111111111111101 #
b1111111111111111111111111111111111111111111111111111111111111101 (
b1 $
#1000
b10 !
b10 )
b1111111111111111111111111111111111111111111111111111111111111100 #
b1111111111111111111111111111111111111111111111111111111111111100 (
b10 $
#1500
b101 !
b101 )
b1111111111111111111111111111111111111111111111111111111111111011 #
b1111111111111111111111111111111111111111111111111111111111111011 (
b11 $
#2000
b100 !
b100 )
b1111111111111111111111111111111111111111111111111111111111111010 #
b1111111111111111111111111111111111111111111111111111111111111010 (
b100 $
#2500
b111 !
b111 )
b1111111111111111111111111111111111111111111111111111111111111001 #
b1111111111111111111111111111111111111111111111111111111111111001 (
b101 $
#3000
b110 !
b110 )
b1111111111111111111111111111111111111111111111111111111111111000 #
b1111111111111111111111111111111111111111111111111111111111111000 (
b110 $
#3500
b1001 !
b1001 )
b1111111111111111111111111111111111111111111111111111111111110111 #
b1111111111111111111111111111111111111111111111111111111111110111 (
b111 $
#4000
b1000 !
b1000 )
b1111111111111111111111111111111111111111111111111111111111110110 #
b1111111111111111111111111111111111111111111111111111111111110110 (
b1000 $
#4500
b1011 !
b1011 )
b1111111111111111111111111111111111111111111111111111111111110101 #
b1111111111111111111111111111111111111111111111111111111111110101 (
b1001 $
#5000
b11 !
b11 )
b1111111111111111111111111111111111111111111111111111111111111101 "
b1111111111111111111111111111111111111111111111111111111111111101 '
b1 %
b1111111111111111111111111111111111111111111111111111111111111110 #
b1111111111111111111111111111111111111111111111111111111111111110 (
b0 $
#5500
b0 !
b0 )
b1111111111111111111111111111111111111111111111111111111111111101 #
b1111111111111111111111111111111111111111111111111111111111111101 (
b1 $
#6000
b1 !
b1 )
b1111111111111111111111111111111111111111111111111111111111111100 #
b1111111111111111111111111111111111111111111111111111111111111100 (
b10 $
#6500
b110 !
b110 )
b1111111111111111111111111111111111111111111111111111111111111011 #
b1111111111111111111111111111111111111111111111111111111111111011 (
b11 $
#7000
b111 !
b111 )
b1111111111111111111111111111111111111111111111111111111111111010 #
b1111111111111111111111111111111111111111111111111111111111111010 (
b100 $
#7500
b100 !
b100 )
b1111111111111111111111111111111111111111111111111111111111111001 #
b1111111111111111111111111111111111111111111111111111111111111001 (
b101 $
#8000
b101 !
b101 )
b1111111111111111111111111111111111111111111111111111111111111000 #
b1111111111111111111111111111111111111111111111111111111111111000 (
b110 $
#8500
b1010 !
b1010 )
b1111111111111111111111111111111111111111111111111111111111110111 #
b1111111111111111111111111111111111111111111111111111111111110111 (
b111 $
#9000
b1011 !
b1011 )
b1111111111111111111111111111111111111111111111111111111111110110 #
b1111111111111111111111111111111111111111111111111111111111110110 (
b1000 $
#9500
b1000 !
b1000 )
b1111111111111111111111111111111111111111111111111111111111110101 #
b1111111111111111111111111111111111111111111111111111111111110101 (
b1001 $
#10000
b10 !
b10 )
b1111111111111111111111111111111111111111111111111111111111111100 "
b1111111111111111111111111111111111111111111111111111111111111100 '
b10 %
b1111111111111111111111111111111111111111111111111111111111111110 #
b1111111111111111111111111111111111111111111111111111111111111110 (
b0 $
#10500
b1 !
b1 )
b1111111111111111111111111111111111111111111111111111111111111101 #
b1111111111111111111111111111111111111111111111111111111111111101 (
b1 $
#11000
b0 !
b0 )
b1111111111111111111111111111111111111111111111111111111111111100 #
b1111111111111111111111111111111111111111111111111111111111111100 (
b10 $
#11500
b111 !
b111 )
b1111111111111111111111111111111111111111111111111111111111111011 #
b1111111111111111111111111111111111111111111111111111111111111011 (
b11 $
#12000
b110 !
b110 )
b1111111111111111111111111111111111111111111111111111111111111010 #
b1111111111111111111111111111111111111111111111111111111111111010 (
b100 $
#12500
b101 !
b101 )
b1111111111111111111111111111111111111111111111111111111111111001 #
b1111111111111111111111111111111111111111111111111111111111111001 (
b101 $
#13000
b100 !
b100 )
b1111111111111111111111111111111111111111111111111111111111111000 #
b1111111111111111111111111111111111111111111111111111111111111000 (
b110 $
#13500
b1011 !
b1011 )
b1111111111111111111111111111111111111111111111111111111111110111 #
b1111111111111111111111111111111111111111111111111111111111110111 (
b111 $
#14000
b1010 !
b1010 )
b1111111111111111111111111111111111111111111111111111111111110110 #
b1111111111111111111111111111111111111111111111111111111111110110 (
b1000 $
#14500
b1001 !
b1001 )
b1111111111111111111111111111111111111111111111111111111111110101 #
b1111111111111111111111111111111111111111111111111111111111110101 (
b1001 $
#15000
b101 !
b101 )
b1111111111111111111111111111111111111111111111111111111111111011 "
b1111111111111111111111111111111111111111111111111111111111111011 '
b11 %
b1111111111111111111111111111111111111111111111111111111111111110 #
b1111111111111111111111111111111111111111111111111111111111111110 (
b0 $
#15500
b110 !
b110 )
b1111111111111111111111111111111111111111111111111111111111111101 #
b1111111111111111111111111111111111111111111111111111111111111101 (
b1 $
#16000
b111 !
b111 )
b1111111111111111111111111111111111111111111111111111111111111100 #
b1111111111111111111111111111111111111111111111111111111111111100 (
b10 $
#16500
b0 !
b0 )
b1111111111111111111111111111111111111111111111111111111111111011 #
b1111111111111111111111111111111111111111111111111111111111111011 (
b11 $
#17000
b1 !
b1 )
b1111111111111111111111111111111111111111111111111111111111111010 #
b1111111111111111111111111111111111111111111111111111111111111010 (
b100 $
#17500
b10 !
b10 )
b1111111111111111111111111111111111111111111111111111111111111001 #
b1111111111111111111111111111111111111111111111111111111111111001 (
b101 $
#18000
b11 !
b11 )
b1111111111111111111111111111111111111111111111111111111111111000 #
b1111111111111111111111111111111111111111111111111111111111111000 (
b110 $
#18500
b1100 !
b1100 )
b1111111111111111111111111111111111111111111111111111111111110111 #
b1111111111111111111111111111111111111111111111111111111111110111 (
b111 $
#19000
b1101 !
b1101 )
b1111111111111111111111111111111111111111111111111111111111110110 #
b1111111111111111111111111111111111111111111111111111111111110110 (
b1000 $
#19500
b1110 !
b1110 )
b1111111111111111111111111111111111111111111111111111111111110101 #
b1111111111111111111111111111111111111111111111111111111111110101 (
b1001 $
#20000
b100 !
b100 )
b1111111111111111111111111111111111111111111111111111111111111010 "
b1111111111111111111111111111111111111111111111111111111111111010 '
b100 %
b1111111111111111111111111111111111111111111111111111111111111110 #
b1111111111111111111111111111111111111111111111111111111111111110 (
b0 $
#20500
b111 !
b111 )
b1111111111111111111111111111111111111111111111111111111111111101 #
b1111111111111111111111111111111111111111111111111111111111111101 (
b1 $
#21000
b110 !
b110 )
b1111111111111111111111111111111111111111111111111111111111111100 #
b1111111111111111111111111111111111111111111111111111111111111100 (
b10 $
#21500
b1 !
b1 )
b1111111111111111111111111111111111111111111111111111111111111011 #
b1111111111111111111111111111111111111111111111111111111111111011 (
b11 $
#22000
b0 !
b0 )
b1111111111111111111111111111111111111111111111111111111111111010 #
b1111111111111111111111111111111111111111111111111111111111111010 (
b100 $
#22500
b11 !
b11 )
b1111111111111111111111111111111111111111111111111111111111111001 #
b1111111111111111111111111111111111111111111111111111111111111001 (
b101 $
#23000
b10 !
b10 )
b1111111111111111111111111111111111111111111111111111111111111000 #
b1111111111111111111111111111111111111111111111111111111111111000 (
b110 $
#23500
b1101 !
b1101 )
b1111111111111111111111111111111111111111111111111111111111110111 #
b1111111111111111111111111111111111111111111111111111111111110111 (
b111 $
#24000
b1100 !
b1100 )
b1111111111111111111111111111111111111111111111111111111111110110 #
b1111111111111111111111111111111111111111111111111111111111110110 (
b1000 $
#24500
b1111 !
b1111 )
b1111111111111111111111111111111111111111111111111111111111110101 #
b1111111111111111111111111111111111111111111111111111111111110101 (
b1001 $
#25000
b111 !
b111 )
b1111111111111111111111111111111111111111111111111111111111111001 "
b1111111111111111111111111111111111111111111111111111111111111001 '
b101 %
b1111111111111111111111111111111111111111111111111111111111111110 #
b1111111111111111111111111111111111111111111111111111111111111110 (
b0 $
#25500
b100 !
b100 )
b1111111111111111111111111111111111111111111111111111111111111101 #
b1111111111111111111111111111111111111111111111111111111111111101 (
b1 $
#26000
b101 !
b101 )
b1111111111111111111111111111111111111111111111111111111111111100 #
b1111111111111111111111111111111111111111111111111111111111111100 (
b10 $
#26500
b10 !
b10 )
b1111111111111111111111111111111111111111111111111111111111111011 #
b1111111111111111111111111111111111111111111111111111111111111011 (
b11 $
#27000
b11 !
b11 )
b1111111111111111111111111111111111111111111111111111111111111010 #
b1111111111111111111111111111111111111111111111111111111111111010 (
b100 $
#27500
b0 !
b0 )
b1111111111111111111111111111111111111111111111111111111111111001 #
b1111111111111111111111111111111111111111111111111111111111111001 (
b101 $
#28000
b1 !
b1 )
b1111111111111111111111111111111111111111111111111111111111111000 #
b1111111111111111111111111111111111111111111111111111111111111000 (
b110 $
#28500
b1110 !
b1110 )
b1111111111111111111111111111111111111111111111111111111111110111 #
b1111111111111111111111111111111111111111111111111111111111110111 (
b111 $
#29000
b1111 !
b1111 )
b1111111111111111111111111111111111111111111111111111111111110110 #
b1111111111111111111111111111111111111111111111111111111111110110 (
b1000 $
#29500
b1100 !
b1100 )
b1111111111111111111111111111111111111111111111111111111111110101 #
b1111111111111111111111111111111111111111111111111111111111110101 (
b1001 $
#30000
b110 !
b110 )
b1111111111111111111111111111111111111111111111111111111111111000 "
b1111111111111111111111111111111111111111111111111111111111111000 '
b110 %
b1111111111111111111111111111111111111111111111111111111111111110 #
b1111111111111111111111111111111111111111111111111111111111111110 (
b0 $
#30500
b101 !
b101 )
b1111111111111111111111111111111111111111111111111111111111111101 #
b1111111111111111111111111111111111111111111111111111111111111101 (
b1 $
#31000
b100 !
b100 )
b1111111111111111111111111111111111111111111111111111111111111100 #
b1111111111111111111111111111111111111111111111111111111111111100 (
b10 $
#31500
b11 !
b11 )
b1111111111111111111111111111111111111111111111111111111111111011 #
b1111111111111111111111111111111111111111111111111111111111111011 (
b11 $
#32000
b10 !
b10 )
b1111111111111111111111111111111111111111111111111111111111111010 #
b1111111111111111111111111111111111111111111111111111111111111010 (
b100 $
#32500
b1 !
b1 )
b1111111111111111111111111111111111111111111111111111111111111001 #
b1111111111111111111111111111111111111111111111111111111111111001 (
b101 $
#33000
b0 !
b0 )
b1111111111111111111111111111111111111111111111111111111111111000 #
b1111111111111111111111111111111111111111111111111111111111111000 (
b110 $
#33500
b1111 !
b1111 )
b1111111111111111111111111111111111111111111111111111111111110111 #
b1111111111111111111111111111111111111111111111111111111111110111 (
b111 $
#34000
b1110 !
b1110 )
b1111111111111111111111111111111111111111111111111111111111110110 #
b1111111111111111111111111111111111111111111111111111111111110110 (
b1000 $
#34500
b1101 !
b1101 )
b1111111111111111111111111111111111111111111111111111111111110101 #
b1111111111111111111111111111111111111111111111111111111111110101 (
b1001 $
#35000
b1001 !
b1001 )
b1111111111111111111111111111111111111111111111111111111111110111 "
b1111111111111111111111111111111111111111111111111111111111110111 '
b111 %
b1111111111111111111111111111111111111111111111111111111111111110 #
b1111111111111111111111111111111111111111111111111111111111111110 (
b0 $
#35500
b1010 !
b1010 )
b1111111111111111111111111111111111111111111111111111111111111101 #
b1111111111111111111111111111111111111111111111111111111111111101 (
b1 $
#36000
b1011 !
b1011 )
b1111111111111111111111111111111111111111111111111111111111111100 #
b1111111111111111111111111111111111111111111111111111111111111100 (
b10 $
#36500
b1100 !
b1100 )
b1111111111111111111111111111111111111111111111111111111111111011 #
b1111111111111111111111111111111111111111111111111111111111111011 (
b11 $
#37000
b1101 !
b1101 )
b1111111111111111111111111111111111111111111111111111111111111010 #
b1111111111111111111111111111111111111111111111111111111111111010 (
b100 $
#37500
b1110 !
b1110 )
b1111111111111111111111111111111111111111111111111111111111111001 #
b1111111111111111111111111111111111111111111111111111111111111001 (
b101 $
#38000
b1111 !
b1111 )
b1111111111111111111111111111111111111111111111111111111111111000 #
b1111111111111111111111111111111111111111111111111111111111111000 (
b110 $
#38500
b0 !
b0 )
b1111111111111111111111111111111111111111111111111111111111110111 #
b1111111111111111111111111111111111111111111111111111111111110111 (
b111 $
#39000
b1 !
b1 )
b1111111111111111111111111111111111111111111111111111111111110110 #
b1111111111111111111111111111111111111111111111111111111111110110 (
b1000 $
#39500
b10 !
b10 )
b1111111111111111111111111111111111111111111111111111111111110101 #
b1111111111111111111111111111111111111111111111111111111111110101 (
b1001 $
#40000
b1000 !
b1000 )
b1111111111111111111111111111111111111111111111111111111111110110 "
b1111111111111111111111111111111111111111111111111111111111110110 '
b1000 %
b1111111111111111111111111111111111111111111111111111111111111110 #
b1111111111111111111111111111111111111111111111111111111111111110 (
b0 $
#40500
b1011 !
b1011 )
b1111111111111111111111111111111111111111111111111111111111111101 #
b1111111111111111111111111111111111111111111111111111111111111101 (
b1 $
#41000
b1010 !
b1010 )
b1111111111111111111111111111111111111111111111111111111111111100 #
b1111111111111111111111111111111111111111111111111111111111111100 (
b10 $
#41500
b1101 !
b1101 )
b1111111111111111111111111111111111111111111111111111111111111011 #
b1111111111111111111111111111111111111111111111111111111111111011 (
b11 $
#42000
b1100 !
b1100 )
b1111111111111111111111111111111111111111111111111111111111111010 #
b1111111111111111111111111111111111111111111111111111111111111010 (
b100 $
#42500
b1111 !
b1111 )
b1111111111111111111111111111111111111111111111111111111111111001 #
b1111111111111111111111111111111111111111111111111111111111111001 (
b101 $
#43000
b1110 !
b1110 )
b1111111111111111111111111111111111111111111111111111111111111000 #
b1111111111111111111111111111111111111111111111111111111111111000 (
b110 $
#43500
b1 !
b1 )
b1111111111111111111111111111111111111111111111111111111111110111 #
b1111111111111111111111111111111111111111111111111111111111110111 (
b111 $
#44000
b0 !
b0 )
b1111111111111111111111111111111111111111111111111111111111110110 #
b1111111111111111111111111111111111111111111111111111111111110110 (
b1000 $
#44500
b11 !
b11 )
b1111111111111111111111111111111111111111111111111111111111110101 #
b1111111111111111111111111111111111111111111111111111111111110101 (
b1001 $
#45000
b1011 !
b1011 )
b1111111111111111111111111111111111111111111111111111111111110101 "
b1111111111111111111111111111111111111111111111111111111111110101 '
b1001 %
b1111111111111111111111111111111111111111111111111111111111111110 #
b1111111111111111111111111111111111111111111111111111111111111110 (
b0 $
#45500
b1000 !
b1000 )
b1111111111111111111111111111111111111111111111111111111111111101 #
b1111111111111111111111111111111111111111111111111111111111111101 (
b1 $
#46000
b1001 !
b1001 )
b1111111111111111111111111111111111111111111111111111111111111100 #
b1111111111111111111111111111111111111111111111111111111111111100 (
b10 $
#46500
b1110 !
b1110 )
b1111111111111111111111111111111111111111111111111111111111111011 #
b1111111111111111111111111111111111111111111111111111111111111011 (
b11 $
#47000
b1111 !
b1111 )
b1111111111111111111111111111111111111111111111111111111111111010 #
b1111111111111111111111111111111111111111111111111111111111111010 (
b100 $
#47500
b1100 !
b1100 )
b1111111111111111111111111111111111111111111111111111111111111001 #
b1111111111111111111111111111111111111111111111111111111111111001 (
b101 $
#48000
b1101 !
b1101 )
b1111111111111111111111111111111111111111111111111111111111111000 #
b1111111111111111111111111111111111111111111111111111111111111000 (
b110 $
#48500
b10 !
b10 )
b1111111111111111111111111111111111111111111111111111111111110111 #
b1111111111111111111111111111111111111111111111111111111111110111 (
b111 $
#49000
b11 !
b11 )
b1111111111111111111111111111111111111111111111111111111111110110 #
b1111111111111111111111111111111111111111111111111111111111110110 (
b1000 $
#49500
b0 !
b0 )
b1111111111111111111111111111111111111111111111111111111111110101 #
b1111111111111111111111111111111111111111111111111111111111110101 (
b1001 $
#50000
b1010 !
b1010 )
b1010 %
b1111111111111111111111111111111111111111111111111111111111111111 #
b1111111111111111111111111111111111111111111111111111111111111111 (
b1010 $
