ALU/ADDER/full_adder.v
module full_adder(a,b,c,sum,carry);

input a;
input b;
input c;
output sum;
output carry;

wire o4,o3,o5;

xor a_xor_b(o4,a,b);
and a_and_b(o3,a,b);

xor sum0(sum,o4,c);
and temp(o5,o4,c);

or carry0(carry,o3,o5);

endmodule

ALU/ADDER/adder_64.v
`include "../ALU/ADDER/full_adder.v"

module adder_64(a,b,sum,overflow,carry);

input signed [63:0] a;
input signed [63:0] b;

output signed [63:0] sum;
output overflow,carry;

wire [63:0] c0;
assign c0[0]= 1'b0;

genvar i;

generate
for(i=0;i<63;i=i+1)
begin
  
    full_adder testing(.a(a[i]),
    .b(b[i]),
    .c(c0[i]),
    .sum(sum[i]),
    .carry(c0[i+1]));
    // $monitor("%b",sum[i]);

end
endgenerate

full_adder testing(.a(a[63]),
.b(b[63]),
.c(c0[63]),
.sum(sum[63]),
.carry(carry));

xor overflow_flag(overflow , carry,c0[63]);

endmodule

ALU/ADDER/adder_test.v
`timescale 1ns/10ps
`include "adder_64.v"

module adder_test;

reg signed [63:0] a;
reg signed [63:0] b;
reg [64:0] ans;

wire signed [63:0] sum;
wire overflow, carry;

adder_64 tt(
.a(a),
.b(b),
.sum(sum),
.overflow(overflow),
.carry(carry));

always @ (a or b) begin
    ans = a+b;
end

integer k,j,m=1;

initial begin

    $dumpfile("adder_test.vcd");
    $dumpvars(0,adder_test);
    $monitor($time,"\nA=%b\nB=%b\nSum=%b\nAns:%b\nOverflow=%b\n", a,b,sum,ans,overflow);
    
    a = 64'b1111111111111111111111111111111111111111111111111111111111111111;
    b = 64'b1111111111111111111111111111111111111111111111111111111111111111;

    #5;

    for(k = 0; k < 5; k = k + 1)
    begin
        b = 64'b1111111111111111111111111111111111111111111111111111111111111111;
        a=a-1;
        #5;
        for(j = 0; j < 5; j = j + 1)
        begin
            b = b-1;
            #5;
        end
        
    end
    a = 64'b0111111111111111111111111111111111111111111111111111111111111111;
    b = 64'b0111111111111111111111111111111111111111111111111111111111111111;
    #5;

    a = 64'b1000000000000000000000000000000000000000000000000000000000000001;
    b = 64'b1000000000000000000000000000000000000000000000000000000000000001;
    #5;
end
  
endmodule

ALU/ADDER/adder_test.vcd
$date
	Tue Jan 24 15:03:51 2023
$end
$version
	Icarus Verilog
$end
$timescale
	10ps
$end
$scope module adder_test $end
$var wire 64 ! sum [63:0] $end
$var wire 1 " overflow $end
$var wire 1 # carry $end
$var reg 64 $ a [63:0] $end
$var reg 65 % ans [64:0] $end
$var reg 64 & b [63:0] $end
$var integer 32 ' j [31:0] $end
$var integer 32 ( k [31:0] $end
$var integer 32 ) m [31:0] $end
$scope module tt $end
$var wire 64 * a [63:0] $end
$var wire 64 + b [63:0] $end
$var wire 1 " overflow $end
$var wire 64 , sum [63:0] $end
$var wire 1 # carry $end
$var wire 64 - c0 [63:0] $end
$scope begin genblk1[0] $end
$scope module testing $end
$var wire 1 . a $end
$var wire 1 / b $end
$var wire 1 0 c $end
$var wire 1 1 carry $end
$var wire 1 2 o3 $end
$var wire 1 3 o4 $end
$var wire 1 4 o5 $end
$var wire 1 5 sum $end
$upscope $end
$upscope $end
$scope begin genblk1[1] $end
$scope module testing $end
$var wire 1 6 a $end
$var wire 1 7 b $end
$var wire 1 8 c $end
$var wire 1 9 carry $end
$var wire 1 : o3 $end
$var wire 1 ; o4 $end
$var wire 1 < o5 $end
$var wire 1 = sum $end
$upscope $end
$upscope $end
$scope begin genblk1[2] $end
$scope module testing $end
$var wire 1 > a $end
$var wire 1 ? b $end
$var wire 1 @ c $end
$var wire 1 A carry $end
$var wire 1 B o3 $end
$var wire 1 C o4 $end
$var wire 1 D o5 $end
$var wire 1 E sum $end
$upscope $end
$upscope $end
$scope begin genblk1[3] $end
$scope module testing $end
$var wire 1 F a $end
$var wire 1 G b $end
$var wire 1 H c $end
$var wire 1 I carry $end
$var wire 1 J o3 $end
$var wire 1 K o4 $end
$var wire 1 L o5 $end
$var wire 1 M sum $end
$upscope $end
$upscope $end
$scope begin genblk1[4] $end
$scope module testing $end
$var wire 1 N a $end
$var wire 1 O b $end
$var wire 1 P c $end
$var wire 1 Q carry $end
$var wire 1 R o3 $end
$var wire 1 S o4 $end
$var wire 1 T o5 $end
$var wire 1 U sum $end
$upscope $end
$upscope $end
$scope begin genblk1[5] $end
$scope module testing $end
$var wire 1 V a $end
$var wire 1 W b $end
$var wire 1 X c $end
$var wire 1 Y carry $end
$var wire 1 Z o3 $end
$var wire 1 [ o4 $end
$var wire 1 \ o5 $end
$var wire 1 ] sum $end
$upscope $end
$upscope $end
$scope begin genblk1[6] $end
$scope module testing $end
$var wire 1 ^ a $end
$var wire 1 _ b $end
$var wire 1 ` c $end
$var wire 1 a carry $end
$var wire 1 b o3 $end
$var wire 1 c o4 $end
$var wire 1 d o5 $end
$var wire 1 e sum $end
$upscope $end
$upscope $end
$scope begin genblk1[7] $end
$scope module testing $end
$var wire 1 f a $end
$var wire 1 g b $end
$var wire 1 h c $end
$var wire 1 i carry $end
$var wire 1 j o3 $end
$var wire 1 k o4 $end
$var wire 1 l o5 $end
$var wire 1 m sum $end
$upscope $end
$upscope $end
$scope begin genblk1[8] $end
$scope module testing $end
$var wire 1 n a $end
$var wire 1 o b $end
$var wire 1 p c $end
$var wire 1 q carry $end
$var wire 1 r o3 $end
$var wire 1 s o4 $end
$var wire 1 t o5 $end
$var wire 1 u sum $end
$upscope $end
$upscope $end
$scope begin genblk1[9] $end
$scope module testing $end
$var wire 1 v a $end
$var wire 1 w b $end
$var wire 1 x c $end
$var wire 1 y carry $end
$var wire 1 z o3 $end
$var wire 1 { o4 $end
$var wire 1 | o5 $end
$var wire 1 } sum $end
$upscope $end
$upscope $end
$scope begin genblk1[10] $end
$scope module testing $end
$var wire 1 ~ a $end
$var wire 1 !" b $end
$var wire 1 "" c $end
$var wire 1 #" carry $end
$var wire 1 $" o3 $end
$var wire 1 %" o4 $end
$var wire 1 &" o5 $end
$var wire 1 '" sum $end
$upscope $end
$upscope $end
$scope begin genblk1[11] $end
$scope module testing $end
$var wire 1 (" a $end
$var wire 1 )" b $end
$var wire 1 *" c $end
$var wire 1 +" carry $end
$var wire 1 ," o3 $end
$var wire 1 -" o4 $end
$var wire 1 ." o5 $end
$var wire 1 /" sum $end
$upscope $end
$upscope $end
$scope begin genblk1[12] $end
$scope module testing $end
$var wire 1 0" a $end
$var wire 1 1" b $end
$var wire 1 2" c $end
$var wire 1 3" carry $end
$var wire 1 4" o3 $end
$var wire 1 5" o4 $end
$var wire 1 6" o5 $end
$var wire 1 7" sum $end
$upscope $end
$upscope $end
$scope begin genblk1[13] $end
$scope module testing $end
$var wire 1 8" a $end
$var wire 1 9" b $end
$var wire 1 :" c $end
$var wire 1 ;" carry $end
$var wire 1 <" o3 $end
$var wire 1 =" o4 $end
$var wire 1 >" o5 $end
$var wire 1 ?" sum $end
$upscope $end
$upscope $end
$scope begin genblk1[14] $end
$scope module testing $end
$var wire 1 @" a $end
$var wire 1 A" b $end
$var wire 1 B" c $end
$var wire 1 C" carry $end
$var wire 1 D" o3 $end
$var wire 1 E" o4 $end
$var wire 1 F" o5 $end
$var wire 1 G" sum $end
$upscope $end
$upscope $end
$scope begin genblk1[15] $end
$scope module testing $end
$var wire 1 H" a $end
$var wire 1 I" b $end
$var wire 1 J" c $end
$var wire 1 K" carry $end
$var wire 1 L" o3 $end
$var wire 1 M" o4 $end
$var wire 1 N" o5 $end
$var wire 1 O" sum $end
$upscope $end
$upscope $end
$scope begin genblk1[16] $end
$scope module testing $end
$var wire 1 P" a $end
$var wire 1 Q" b $end
$var wire 1 R" c $end
$var wire 1 S" carry $end
$var wire 1 T" o3 $end
$var wire 1 U" o4 $end
$var wire 1 V" o5 $end
$var wire 1 W" sum $end
$upscope $end
$upscope $end
$scope begin genblk1[17] $end
$scope module testing $end
$var wire 1 X" a $end
$var wire 1 Y" b $end
$var wire 1 Z" c $end
$var wire 1 [" carry $end
$var wire 1 \" o3 $end
$var wire 1 ]" o4 $end
$var wire 1 ^" o5 $end
$var wire 1 _" sum $end
$upscope $end
$upscope $end
$scope begin genblk1[18] $end
$scope module testing $end
$var wire 1 `" a $end
$var wire 1 a" b $end
$var wire 1 b" c $end
$var wire 1 c" carry $end
$var wire 1 d" o3 $end
$var wire 1 e" o4 $end
$var wire 1 f" o5 $end
$var wire 1 g" sum $end
$upscope $end
$upscope $end
$scope begin genblk1[19] $end
$scope module testing $end
$var wire 1 h" a $end
$var wire 1 i" b $end
$var wire 1 j" c $end
$var wire 1 k" carry $end
$var wire 1 l" o3 $end
$var wire 1 m" o4 $end
$var wire 1 n" o5 $end
$var wire 1 o" sum $end
$upscope $end
$upscope $end
$scope begin genblk1[20] $end
$scope module testing $end
$var wire 1 p" a $end
$var wire 1 q" b $end
$var wire 1 r" c $end
$var wire 1 s" carry $end
$var wire 1 t" o3 $end
$var wire 1 u" o4 $end
$var wire 1 v" o5 $end
$var wire 1 w" sum $end
$upscope $end
$upscope $end
$scope begin genblk1[21] $end
$scope module testing $end
$var wire 1 x" a $end
$var wire 1 y" b $end
$var wire 1 z" c $end
$var wire 1 {" carry $end
$var wire 1 |" o3 $end
$var wire 1 }" o4 $end
$var wire 1 ~" o5 $end
$var wire 1 !# sum $end
$upscope $end
$upscope $end
$scope begin genblk1[22] $end
$scope module testing $end
$var wire 1 "# a $end
$var wire 1 ## b $end
$var wire 1 $# c $end
$var wire 1 %# carry $end
$var wire 1 &# o3 $end
$var wire 1 '# o4 $end
$var wire 1 (# o5 $end
$var wire 1 )# sum $end
$upscope $end
$upscope $end
$scope begin genblk1[23] $end
$scope module testing $end
$var wire 1 *# a $end
$var wire 1 +# b $end
$var wire 1 ,# c $end
$var wire 1 -# carry $end
$var wire 1 .# o3 $end
$var wire 1 /# o4 $end
$var wire 1 0# o5 $end
$var wire 1 1# sum $end
$upscope $end
$upscope $end
$scope begin genblk1[24] $end
$scope module testing $end
$var wire 1 2# a $end
$var wire 1 3# b $end
$var wire 1 4# c $end
$var wire 1 5# carry $end
$var wire 1 6# o3 $end
$var wire 1 7# o4 $end
$var wire 1 8# o5 $end
$var wire 1 9# sum $end
$upscope $end
$upscope $end
$scope begin genblk1[25] $end
$scope module testing $end
$var wire 1 :# a $end
$var wire 1 ;# b $end
$var wire 1 <# c $end
$var wire 1 =# carry $end
$var wire 1 ># o3 $end
$var wire 1 ?# o4 $end
$var wire 1 @# o5 $end
$var wire 1 A# sum $end
$upscope $end
$upscope $end
$scope begin genblk1[26] $end
$scope module testing $end
$var wire 1 B# a $end
$var wire 1 C# b $end
$var wire 1 D# c $end
$var wire 1 E# carry $end
$var wire 1 F# o3 $end
$var wire 1 G# o4 $end
$var wire 1 H# o5 $end
$var wire 1 I# sum $end
$upscope $end
$upscope $end
$scope begin genblk1[27] $end
$scope module testing $end
$var wire 1 J# a $end
$var wire 1 K# b $end
$var wire 1 L# c $end
$var wire 1 M# carry $end
$var wire 1 N# o3 $end
$var wire 1 O# o4 $end
$var wire 1 P# o5 $end
$var wire 1 Q# sum $end
$upscope $end
$upscope $end
$scope begin genblk1[28] $end
$scope module testing $end
$var wire 1 R# a $end
$var wire 1 S# b $end
$var wire 1 T# c $end
$var wire 1 U# carry $end
$var wire 1 V# o3 $end
$var wire 1 W# o4 $end
$var wire 1 X# o5 $end
$var wire 1 Y# sum $end
$upscope $end
$upscope $end
$scope begin genblk1[29] $end
$scope module testing $end
$var wire 1 Z# a $end
$var wire 1 [# b $end
$var wire 1 \# c $end
$var wire 1 ]# carry $end
$var wire 1 ^# o3 $end
$var wire 1 _# o4 $end
$var wire 1 `# o5 $end
$var wire 1 a# sum $end
$upscope $end
$upscope $end
$scope begin genblk1[30] $end
$scope module testing $end
$var wire 1 b# a $end
$var wire 1 c# b $end
$var wire 1 d# c $end
$var wire 1 e# carry $end
$var wire 1 f# o3 $end
$var wire 1 g# o4 $end
$var wire 1 h# o5 $end
$var wire 1 i# sum $end
$upscope $end
$upscope $end
$scope begin genblk1[31] $end
$scope module testing $end
$var wire 1 j# a $end
$var wire 1 k# b $end
$var wire 1 l# c $end
$var wire 1 m# carry $end
$var wire 1 n# o3 $end
$var wire 1 o# o4 $end
$var wire 1 p# o5 $end
$var wire 1 q# sum $end
$upscope $end
$upscope $end
$scope begin genblk1[32] $end
$scope module testing $end
$var wire 1 r# a $end
$var wire 1 s# b $end
$var wire 1 t# c $end
$var wire 1 u# carry $end
$var wire 1 v# o3 $end
$var wire 1 w# o4 $end
$var wire 1 x# o5 $end
$var wire 1 y# sum $end
$upscope $end
$upscope $end
$scope begin genblk1[33] $end
$scope module testing $end
$var wire 1 z# a $end
$var wire 1 {# b $end
$var wire 1 |# c $end
$var wire 1 }# carry $end
$var wire 1 ~# o3 $end
$var wire 1 !$ o4 $end
$var wire 1 "$ o5 $end
$var wire 1 #$ sum $end
$upscope $end
$upscope $end
$scope begin genblk1[34] $end
$scope module testing $end
$var wire 1 $$ a $end
$var wire 1 %$ b $end
$var wire 1 &$ c $end
$var wire 1 '$ carry $end
$var wire 1 ($ o3 $end
$var wire 1 )$ o4 $end
$var wire 1 *$ o5 $end
$var wire 1 +$ sum $end
$upscope $end
$upscope $end
$scope begin genblk1[35] $end
$scope module testing $end
$var wire 1 ,$ a $end
$var wire 1 -$ b $end
$var wire 1 .$ c $end
$var wire 1 /$ carry $end
$var wire 1 0$ o3 $end
$var wire 1 1$ o4 $end
$var wire 1 2$ o5 $end
$var wire 1 3$ sum $end
$upscope $end
$upscope $end
$scope begin genblk1[36] $end
$scope module testing $end
$var wire 1 4$ a $end
$var wire 1 5$ b $end
$var wire 1 6$ c $end
$var wire 1 7$ carry $end
$var wire 1 8$ o3 $end
$var wire 1 9$ o4 $end
$var wire 1 :$ o5 $end
$var wire 1 ;$ sum $end
$upscope $end
$upscope $end
$scope begin genblk1[37] $end
$scope module testing $end
$var wire 1 <$ a $end
$var wire 1 =$ b $end
$var wire 1 >$ c $end
$var wire 1 ?$ carry $end
$var wire 1 @$ o3 $end
$var wire 1 A$ o4 $end
$var wire 1 B$ o5 $end
$var wire 1 C$ sum $end
$upscope $end
$upscope $end
$scope begin genblk1[38] $end
$scope module testing $end
$var wire 1 D$ a $end
$var wire 1 E$ b $end
$var wire 1 F$ c $end
$var wire 1 G$ carry $end
$var wire 1 H$ o3 $end
$var wire 1 I$ o4 $end
$var wire 1 J$ o5 $end
$var wire 1 K$ sum $end
$upscope $end
$upscope $end
$scope begin genblk1[39] $end
$scope module testing $end
$var wire 1 L$ a $end
$var wire 1 M$ b $end
$var wire 1 N$ c $end
$var wire 1 O$ carry $end
$var wire 1 P$ o3 $end
$var wire 1 Q$ o4 $end
$var wire 1 R$ o5 $end
$var wire 1 S$ sum $end
$upscope $end
$upscope $end
$scope begin genblk1[40] $end
$scope module testing $end
$var wire 1 T$ a $end
$var wire 1 U$ b $end
$var wire 1 V$ c $end
$var wire 1 W$ carry $end
$var wire 1 X$ o3 $end
$var wire 1 Y$ o4 $end
$var wire 1 Z$ o5 $end
$var wire 1 [$ sum $end
$upscope $end
$upscope $end
$scope begin genblk1[41] $end
$scope module testing $end
$var wire 1 \$ a $end
$var wire 1 ]$ b $end
$var wire 1 ^$ c $end
$var wire 1 _$ carry $end
$var wire 1 `$ o3 $end
$var wire 1 a$ o4 $end
$var wire 1 b$ o5 $end
$var wire 1 c$ sum $end
$upscope $end
$upscope $end
$scope begin genblk1[42] $end
$scope module testing $end
$var wire 1 d$ a $end
$var wire 1 e$ b $end
$var wire 1 f$ c $end
$var wire 1 g$ carry $end
$var wire 1 h$ o3 $end
$var wire 1 i$ o4 $end
$var wire 1 j$ o5 $end
$var wire 1 k$ sum $end
$upscope $end
$upscope $end
$scope begin genblk1[43] $end
$scope module testing $end
$var wire 1 l$ a $end
$var wire 1 m$ b $end
$var wire 1 n$ c $end
$var wire 1 o$ carry $end
$var wire 1 p$ o3 $end
$var wire 1 q$ o4 $end
$var wire 1 r$ o5 $end
$var wire 1 s$ sum $end
$upscope $end
$upscope $end
$scope begin genblk1[44] $end
$scope module testing $end
$var wire 1 t$ a $end
$var wire 1 u$ b $end
$var wire 1 v$ c $end
$var wire 1 w$ carry $end
$var wire 1 x$ o3 $end
$var wire 1 y$ o4 $end
$var wire 1 z$ o5 $end
$var wire 1 {$ sum $end
$upscope $end
$upscope $end
$scope begin genblk1[45] $end
$scope module testing $end
$var wire 1 |$ a $end
$var wire 1 }$ b $end
$var wire 1 ~$ c $end
$var wire 1 !% carry $end
$var wire 1 "% o3 $end
$var wire 1 #% o4 $end
$var wire 1 $% o5 $end
$var wire 1 %% sum $end
$upscope $end
$upscope $end
$scope begin genblk1[46] $end
$scope module testing $end
$var wire 1 &% a $end
$var wire 1 '% b $end
$var wire 1 (% c $end
$var wire 1 )% carry $end
$var wire 1 *% o3 $end
$var wire 1 +% o4 $end
$var wire 1 ,% o5 $end
$var wire 1 -% sum $end
$upscope $end
$upscope $end
$scope begin genblk1[47] $end
$scope module testing $end
$var wire 1 .% a $end
$var wire 1 /% b $end
$var wire 1 0% c $end
$var wire 1 1% carry $end
$var wire 1 2% o3 $end
$var wire 1 3% o4 $end
$var wire 1 4% o5 $end
$var wire 1 5% sum $end
$upscope $end
$upscope $end
$scope begin genblk1[48] $end
$scope module testing $end
$var wire 1 6% a $end
$var wire 1 7% b $end
$var wire 1 8% c $end
$var wire 1 9% carry $end
$var wire 1 :% o3 $end
$var wire 1 ;% o4 $end
$var wire 1 <% o5 $end
$var wire 1 =% sum $end
$upscope $end
$upscope $end
$scope begin genblk1[49] $end
$scope module testing $end
$var wire 1 >% a $end
$var wire 1 ?% b $end
$var wire 1 @% c $end
$var wire 1 A% carry $end
$var wire 1 B% o3 $end
$var wire 1 C% o4 $end
$var wire 1 D% o5 $end
$var wire 1 E% sum $end
$upscope $end
$upscope $end
$scope begin genblk1[50] $end
$scope module testing $end
$var wire 1 F% a $end
$var wire 1 G% b $end
$var wire 1 H% c $end
$var wire 1 I% carry $end
$var wire 1 J% o3 $end
$var wire 1 K% o4 $end
$var wire 1 L% o5 $end
$var wire 1 M% sum $end
$upscope $end
$upscope $end
$scope begin genblk1[51] $end
$scope module testing $end
$var wire 1 N% a $end
$var wire 1 O% b $end
$var wire 1 P% c $end
$var wire 1 Q% carry $end
$var wire 1 R% o3 $end
$var wire 1 S% o4 $end
$var wire 1 T% o5 $end
$var wire 1 U% sum $end
$upscope $end
$upscope $end
$scope begin genblk1[52] $end
$scope module testing $end
$var wire 1 V% a $end
$var wire 1 W% b $end
$var wire 1 X% c $end
$var wire 1 Y% carry $end
$var wire 1 Z% o3 $end
$var wire 1 [% o4 $end
$var wire 1 \% o5 $end
$var wire 1 ]% sum $end
$upscope $end
$upscope $end
$scope begin genblk1[53] $end
$scope module testing $end
$var wire 1 ^% a $end
$var wire 1 _% b $end
$var wire 1 `% c $end
$var wire 1 a% carry $end
$var wire 1 b% o3 $end
$var wire 1 c% o4 $end
$var wire 1 d% o5 $end
$var wire 1 e% sum $end
$upscope $end
$upscope $end
$scope begin genblk1[54] $end
$scope module testing $end
$var wire 1 f% a $end
$var wire 1 g% b $end
$var wire 1 h% c $end
$var wire 1 i% carry $end
$var wire 1 j% o3 $end
$var wire 1 k% o4 $end
$var wire 1 l% o5 $end
$var wire 1 m% sum $end
$upscope $end
$upscope $end
$scope begin genblk1[55] $end
$scope module testing $end
$var wire 1 n% a $end
$var wire 1 o% b $end
$var wire 1 p% c $end
$var wire 1 q% carry $end
$var wire 1 r% o3 $end
$var wire 1 s% o4 $end
$var wire 1 t% o5 $end
$var wire 1 u% sum $end
$upscope $end
$upscope $end
$scope begin genblk1[56] $end
$scope module testing $end
$var wire 1 v% a $end
$var wire 1 w% b $end
$var wire 1 x% c $end
$var wire 1 y% carry $end
$var wire 1 z% o3 $end
$var wire 1 {% o4 $end
$var wire 1 |% o5 $end
$var wire 1 }% sum $end
$upscope $end
$upscope $end
$scope begin genblk1[57] $end
$scope module testing $end
$var wire 1 ~% a $end
$var wire 1 !& b $end
$var wire 1 "& c $end
$var wire 1 #& carry $end
$var wire 1 $& o3 $end
$var wire 1 %& o4 $end
$var wire 1 && o5 $end
$var wire 1 '& sum $end
$upscope $end
$upscope $end
$scope begin genblk1[58] $end
$scope module testing $end
$var wire 1 (& a $end
$var wire 1 )& b $end
$var wire 1 *& c $end
$var wire 1 +& carry $end
$var wire 1 ,& o3 $end
$var wire 1 -& o4 $end
$var wire 1 .& o5 $end
$var wire 1 /& sum $end
$upscope $end
$upscope $end
$scope begin genblk1[59] $end
$scope module testing $end
$var wire 1 0& a $end
$var wire 1 1& b $end
$var wire 1 2& c $end
$var wire 1 3& carry $end
$var wire 1 4& o3 $end
$var wire 1 5& o4 $end
$var wire 1 6& o5 $end
$var wire 1 7& sum $end
$upscope $end
$upscope $end
$scope begin genblk1[60] $end
$scope module testing $end
$var wire 1 8& a $end
$var wire 1 9& b $end
$var wire 1 :& c $end
$var wire 1 ;& carry $end
$var wire 1 <& o3 $end
$var wire 1 =& o4 $end
$var wire 1 >& o5 $end
$var wire 1 ?& sum $end
$upscope $end
$upscope $end
$scope begin genblk1[61] $end
$scope module testing $end
$var wire 1 @& a $end
$var wire 1 A& b $end
$var wire 1 B& c $end
$var wire 1 C& carry $end
$var wire 1 D& o3 $end
$var wire 1 E& o4 $end
$var wire 1 F& o5 $end
$var wire 1 G& sum $end
$upscope $end
$upscope $end
$scope begin genblk1[62] $end
$scope module testing $end
$var wire 1 H& a $end
$var wire 1 I& b $end
$var wire 1 J& c $end
$var wire 1 K& carry $end
$var wire 1 L& o3 $end
$var wire 1 M& o4 $end
$var wire 1 N& o5 $end
$var wire 1 O& sum $end
$upscope $end
$upscope $end
$scope module testing $end
$var wire 1 P& a $end
$var wire 1 Q& b $end
$var wire 1 R& c $end
$var wire 1 # carry $end
$var wire 1 S& o3 $end
$var wire 1 T& o4 $end
$var wire 1 U& o5 $end
$var wire 1 V& sum $end
$upscope $end
$upscope $end
$upscope $end
$enddefinitions $end
#0
$dumpvars
1V&
0U&
0T&
1S&
1R&
1Q&
1P&
1O&
0N&
0M&
1L&
1K&
1J&
1I&
1H&
1G&
0F&
0E&
1D&
1C&
1B&
1A&
1@&
1?&
0>&
0=&
1<&
1;&
1:&
19&
18&
17&
06&
05&
14&
13&
12&
11&
10&
1/&
0.&
0-&
1,&
1+&
1*&
1)&
1(&
1'&
0&&
0%&
1$&
1#&
1"&
1!&
1~%
1}%
0|%
0{%
1z%
1y%
1x%
1w%
1v%
1u%
0t%
0s%
1r%
1q%
1p%
1o%
1n%
1m%
0l%
0k%
1j%
1i%
1h%
1g%
1f%
1e%
0d%
0c%
1b%
1a%
1`%
1_%
1^%
1]%
0\%
0[%
1Z%
1Y%
1X%
1W%
1V%
1U%
0T%
0S%
1R%
1Q%
1P%
1O%
1N%
1M%
0L%
0K%
1J%
1I%
1H%
1G%
1F%
1E%
0D%
0C%
1B%
1A%
1@%
1?%
1>%
1=%
0<%
0;%
1:%
19%
18%
17%
16%
15%
04%
03%
12%
11%
10%
1/%
1.%
1-%
0,%
0+%
1*%
1)%
1(%
1'%
1&%
1%%
0$%
0#%
1"%
1!%
1~$
1}$
1|$
1{$
0z$
0y$
1x$
1w$
1v$
1u$
1t$
1s$
0r$
0q$
1p$
1o$
1n$
1m$
1l$
1k$
0j$
0i$
1h$
1g$
1f$
1e$
1d$
1c$
0b$
0a$
1`$
1_$
1^$
1]$
1\$
1[$
0Z$
0Y$
1X$
1W$
1V$
1U$
1T$
1S$
0R$
0Q$
1P$
1O$
1N$
1M$
1L$
1K$
0J$
0I$
1H$
1G$
1F$
1E$
1D$
1C$
0B$
0A$
1@$
1?$
1>$
1=$
1<$
1;$
0:$
09$
18$
17$
16$
15$
14$
13$
02$
01$
10$
1/$
1.$
1-$
1,$
1+$
0*$
0)$
1($
1'$
1&$
1%$
1$$
1#$
0"$
0!$
1~#
1}#
1|#
1{#
1z#
1y#
0x#
0w#
1v#
1u#
1t#
1s#
1r#
1q#
0p#
0o#
1n#
1m#
1l#
1k#
1j#
1i#
0h#
0g#
1f#
1e#
1d#
1c#
1b#
1a#
0`#
0_#
1^#
1]#
1\#
1[#
1Z#
1Y#
0X#
0W#
1V#
1U#
1T#
1S#
1R#
1Q#
0P#
0O#
1N#
1M#
1L#
1K#
1J#
1I#
0H#
0G#
1F#
1E#
1D#
1C#
1B#
1A#
0@#
0?#
1>#
1=#
1<#
1;#
1:#
19#
08#
07#
16#
15#
14#
13#
12#
11#
00#
0/#
1.#
1-#
1,#
1+#
1*#
1)#
0(#
0'#
1&#
1%#
1$#
1##
1"#
1!#
0~"
0}"
1|"
1{"
1z"
1y"
1x"
1w"
0v"
0u"
1t"
1s"
1r"
1q"
1p"
1o"
0n"
0m"
1l"
1k"
1j"
1i"
1h"
1g"
0f"
0e"
1d"
1c"
1b"
1a"
1`"
1_"
0^"
0]"
1\"
1["
1Z"
1Y"
1X"
1W"
0V"
0U"
1T"
1S"
1R"
1Q"
1P"
1O"
0N"
0M"
1L"
1K"
1J"
1I"
1H"
1G"
0F"
0E"
1D"
1C"
1B"
1A"
1@"
1?"
0>"
0="
1<"
1;"
1:"
19"
18"
17"
06"
05"
14"
13"
12"
11"
10"
1/"
0."
0-"
1,"
1+"
1*"
1)"
1("
1'"
0&"
0%"
1$"
1#"
1""
1!"
1~
1}
0|
0{
1z
1y
1x
1w
1v
1u
0t
0s
1r
1q
1p
1o
1n
1m
0l
0k
1j
1i
1h
1g
1f
1e
0d
0c
1b
1a
1`
1_
1^
1]
0\
0[
1Z
1Y
1X
1W
1V
1U
0T
0S
1R
1Q
1P
1O
1N
1M
0L
0K
1J
1I
1H
1G
1F
1E
0D
0C
1B
1A
1@
1?
1>
1=
0<
0;
1:
19
18
17
16
05
04
03
12
11
00
1/
1.
b1111111111111111111111111111111111111111111111111111111111111110 -
b1111111111111111111111111111111111111111111111111111111111111110 ,
b1111111111111111111111111111111111111111111111111111111111111111 +
b1111111111111111111111111111111111111111111111111111111111111111 *
b1 )
bx (
bx '
b1111111111111111111111111111111111111111111111111111111111111111 &
b11111111111111111111111111111111111111111111111111111111111111110 %
b1111111111111111111111111111111111111111111111111111111111111111 $
1#
0"
b1111111111111111111111111111111111111111111111111111111111111110 !
$end
#500
0=
08
b1111111111111111111111111111111111111111111111111111111111111101 !
b1111111111111111111111111111111111111111111111111111111111111101 ,
15
b1111111111111111111111111111111111111111111111111111111111111100 -
01
13
02
0.
b11111111111111111111111111111111111111111111111111111111111111101 %
b1111111111111111111111111111111111111111111111111111111111111110 $
b1111111111111111111111111111111111111111111111111111111111111110 *
b0 (
#1000
b1111111111111111111111111111111111111111111111111111111111111100 !
b1111111111111111111111111111111111111111111111111111111111111100 ,
05
03
0/
b11111111111111111111111111111111111111111111111111111111111111100 %
b1111111111111111111111111111111111111111111111111111111111111110 &
b1111111111111111111111111111111111111111111111111111111111111110 +
b0 '
#1500
0E
0@
15
b1111111111111111111111111111111111111111111111111111111111111011 !
b1111111111111111111111111111111111111111111111111111111111111011 ,
1=
b1111111111111111111111111111111111111111111111111111111111111000 -
09
13
1;
0:
1/
07
b11111111111111111111111111111111111111111111111111111111111111011 %
b1111111111111111111111111111111111111111111111111111111111111101 &
b1111111111111111111111111111111111111111111111111111111111111101 +
b1 '
#2000
b1111111111111111111111111111111111111111111111111111111111111010 !
b1111111111111111111111111111111111111111111111111111111111111010 ,
05
03
0/
b11111111111111111111111111111111111111111111111111111111111111010 %
b1111111111111111111111111111111111111111111111111111111111111100 &
b1111111111111111111111111111111111111111111111111111111111111100 +
b10 '
#2500
1D
1M
1@
1H
15
0=
19
b1111111111111111111111111111111111111111111111111111111111111001 !
b1111111111111111111111111111111111111111111111111111111111111001 ,
0E
b1111111111111111111111111111111111111111111111111111111111111100 -
1A
13
0;
1:
1C
0B
1/
17
0?
b11111111111111111111111111111111111111111111111111111111111111001 %
b1111111111111111111111111111111111111111111111111111111111111011 &
b1111111111111111111111111111111111111111111111111111111111111011 +
b11 '
#3000
b1111111111111111111111111111111111111111111111111111111111111000 !
b1111111111111111111111111111111111111111111111111111111111111000 ,
05
03
0/
b11111111111111111111111111111111111111111111111111111111111111000 %
b1111111111111111111111111111111111111111111111111111111111111010 &
b1111111111111111111111111111111111111111111111111111111111111010 +
b100 '
#3500
1<
1@
18
0=
19
b1111111111111111111111111111111111111111111111111111111111111110 -
11
b1111111111111111111111111111111111111111111111111111111111111100 !
b1111111111111111111111111111111111111111111111111111111111111100 ,
1E
0D
1;
0:
12
0C
1B
1.
06
1/
1?
b11111111111111111111111111111111111111111111111111111111111111100 %
b1111111111111111111111111111111111111111111111111111111111111101 $
b1111111111111111111111111111111111111111111111111111111111111101 *
b1111111111111111111111111111111111111111111111111111111111111111 &
b1111111111111111111111111111111111111111111111111111111111111111 +
b1 (
b101 '
#4000
0E
0@
09
1=
0<
08
b1111111111111111111111111111111111111111111111111111111111111011 !
b1111111111111111111111111111111111111111111111111111111111111011 ,
15
b1111111111111111111111111111111111111111111111111111111111111000 -
01
13
02
0/
b11111111111111111111111111111111111111111111111111111111111111011 %
b1111111111111111111111111111111111111111111111111111111111111110 &
b1111111111111111111111111111111111111111111111111111111111111110 +
b0 '
#4500
18
05
b1111111111111111111111111111111111111111111111111111111111111010 -
11
b1111111111111111111111111111111111111111111111111111111111111010 !
b1111111111111111111111111111111111111111111111111111111111111010 ,
1=
03
12
0;
1/
07
b11111111111111111111111111111111111111111111111111111111111111010 %
b1111111111111111111111111111111111111111111111111111111111111101 &
b1111111111111111111111111111111111111111111111111111111111111101 +
b1 '
